[
  {
    "username": "ironspidermatt085z",
    "title": "Gotham Knights",
    "timestamp": "2025-09-08T15:39:10.084408+00:00"
  },
  {
    "username": "DerpyTater_",
    "title": "Yo-kai Watch",
    "timestamp": "2025-09-08T16:13:18.486796+00:00"
  },
  {
    "username": "aWittleGoblin",
    "title": "Digimon Rumble Arena 2",
    "timestamp": "2025-09-08T16:15:54.864224+00:00"
  },
  {
    "username": "Axedanner",
    "title": "Split/Second",
    "timestamp": "2025-09-10T15:02:07.020800+00:00"
  },
  {
    "username": "kerrplunk_",
    "title": "TUNIC",
    "timestamp": "2025-09-10T15:02:23.935588+00:00"
  },
  {
    "username": "Shaun_Da_Bomb",
    "title": "Ninja Gaiden",
    "timestamp": "2025-09-10T15:36:26.736154+00:00"
  },
  {
    "username": "El_Crumpet",
    "title": "Seek and Destroy",
    "timestamp": "2025-09-10T15:43:09.449061+00:00"
  },
  {
    "username": "DerpyTater_",
    "title": "Bloody Roar",
    "timestamp": "2025-09-10T16:01:17.396151+00:00"
  },
  {
    "username": "Shadikennn",
    "title": "Mario Party 3",
    "timestamp": "2025-09-10T16:02:13.503607+00:00"
  },
  {
    "username": "VanOsdelGaia",
    "title": "Rayman 2: Revolution",
    "timestamp": "2025-09-10T16:14:15.078543+00:00"
  }
]